<annotation>
	<folder></folder>
	<filename>person_v3_1210_jpg.rf.455996eedbf76e945b83b5d57e7d1eb5.jpg</filename>
	<path>person_v3_1210_jpg.rf.455996eedbf76e945b83b5d57e7d1eb5.jpg</path>
	<source>
		<database>roboflow.ai</database>
	</source>
	<size>
		<width>300</width>
		<height>300</height>
		<depth>3</depth>
	</size>
	<segmented>0</segmented>
	<object>
		<name>person</name>
		<pose>Unspecified</pose>
		<truncated>0</truncated>
		<difficult>0</difficult>
		<occluded>0</occluded>
		<bndbox>
			<xmin>1</xmin>
			<xmax>280</xmax>
			<ymin>68</ymin>
			<ymax>300</ymax>
		</bndbox>
	</object>
	<object>
		<name>redscarf</name>
		<pose>Unspecified</pose>
		<truncated>0</truncated>
		<difficult>0</difficult>
		<occluded>0</occluded>
		<bndbox>
			<xmin>88</xmin>
			<xmax>176</xmax>
			<ymin>166</ymin>
			<ymax>243</ymax>
		</bndbox>
	</object>
</annotation>
